drf_health_check/__init__.py
drf_health_check/_stub_settings.py
drf_health_check/apps.py
drf_health_check/health_status.py
drf_health_check/serializers.py
drf_health_check/settings.py
drf_health_check/urls.py
drf_health_check/views.py
drf_health_check/providers/__init__.py
drf_health_check/providers/base.py
drf_health_check/providers/db.py
drf_health_check-0.0.12.dist-info/LICENSE
drf_health_check-0.0.12.dist-info/WHEEL
drf_health_check-0.0.12.dist-info/METADATA
drf_health_check-0.0.12.dist-info/RECORD
